libname/__init__.py
libname/buttons.py
libname/main.py
pygame_custom_gui-0.0.1.dist-info/METADATA
pygame_custom_gui-0.0.1.dist-info/WHEEL
pygame_custom_gui-0.0.1.dist-info/top_level.txt
pygame_custom_gui-0.0.1.dist-info/RECORD
