Metadata-Version: 2.1
Name: pygame-custom-gui
Version: 0.0.1
Summary: A customizable button library for pygame
Author: piknall
Author-email: pisafe@tutanota.com
Keywords: python,pygame,gui,buttons
Classifier: Development Status :: 1 - Planning
Classifier: Intended Audience :: Developers
Classifier: Programming Language :: Python :: 3
Classifier: Operating System :: Unix
Classifier: Operating System :: MacOS :: MacOS X
Classifier: Operating System :: Microsoft :: Windows
Requires-Dist: pygame-ce
Requires-Dist: numpy
